ckanserviceprovider/__init__.py
ckanserviceprovider/db.py
ckanserviceprovider/default_settings.py
ckanserviceprovider/job.py
ckanserviceprovider/util.py
ckanserviceprovider/web.py
example/__init__.py
example/jobs.py
example/main.py
ckanserviceprovider-0.0.8.dist-info/LICENSE
ckanserviceprovider-0.0.8.dist-info/METADATA
ckanserviceprovider-0.0.8.dist-info/WHEEL
ckanserviceprovider-0.0.8.dist-info/top_level.txt
ckanserviceprovider-0.0.8.dist-info/RECORD
