Metadata-Version: 2.1
Name: ckanserviceprovider
Version: 0.0.8
Summary: A library for making web services that make functions available as synchronous or asynchronous jobs
Home-page: https://github.com/ckan/ckan-service-provider
Author: UNKNOWN
Author-email: UNKNOWN
License: AGPL
Keywords: ckan
Platform: UNKNOWN
Classifier: Development Status :: 4 - Beta
Classifier: License :: OSI Approved :: GNU Affero General Public License v3 or later (AGPLv3+)
Classifier: Programming Language :: Python :: 2.7
Requires-Dist: APScheduler (<3.0.0,>=2.1.2)
Requires-Dist: Flask (<1.0.0,>=0.11.1)
Requires-Dist: SQLAlchemy (<1.3.0,>=1.2.7)
Requires-Dist: requests (<2.12.0,>=2.11.1)
Requires-Dist: flask-admin (<1.6.0,>=1.5.0)
Requires-Dist: flask-login (<0.4.0,>=0.3.0)
